nanome_realtime_scoring/RealtimeScoring.py
nanome_realtime_scoring/SettingsMenu.py
nanome_realtime_scoring/__init__.py
nanome_realtime_scoring/menu.json
nanome_realtime_scoring/settings.json
nanome_realtime_scoring/dsx/dsx_linux_64.lnx
nanome_realtime_scoring/dsx/libc.so.6
nanome_realtime_scoring/dsx/libgcc_s.so.1
nanome_realtime_scoring/dsx/libm.so.6
nanome_realtime_scoring/dsx/libpthread.so.0
nanome_realtime_scoring/dsx/libstdc++.so.6
nanome_realtime_scoring/dsx/pdb_pot_0511/ligand.def
nanome_realtime_scoring/dsx/pdb_pot_0511/potentials.keys
nanome_realtime_scoring/dsx/pdb_pot_0511/potentials_repulsive.bin
nanome_realtime_scoring/dsx/pdb_pot_0511/pro_sas_potentials.bin
nanome_realtime_scoring/dsx/pdb_pot_0511/pro_sas_potentials.keys
nanome_realtime_scoring/dsx/pdb_pot_0511/protein.def
nanome_realtime_scoring/dsx/pdb_pot_0511/sas_potentials.bin
nanome_realtime_scoring/dsx/pdb_pot_0511/sas_potentials.keys
nanome_realtime_scoring-0.2.5.dist-info/LICENSE
nanome_realtime_scoring-0.2.5.dist-info/METADATA
nanome_realtime_scoring-0.2.5.dist-info/WHEEL
nanome_realtime_scoring-0.2.5.dist-info/entry_points.txt
nanome_realtime_scoring-0.2.5.dist-info/top_level.txt
nanome_realtime_scoring-0.2.5.dist-info/RECORD
