Metadata-Version: 2.1
Name: nanome-realtime-scoring
Version: 0.2.5
Summary: Nanome Plugin displaying docking score of complexes in the workspace, in realtime
Home-page: https://github.com/nanome-ai/plugin-realtime-scoring
Author: Nanome
Author-email: hello@nanome.ai
License: MIT
Keywords: virtual-reality,chemistry,python,api,plugin
Platform: any
Classifier: Development Status :: 3 - Alpha
Classifier: Intended Audience :: Science/Research
Classifier: Topic :: Scientific/Engineering :: Chemistry
Classifier: License :: OSI Approved :: MIT License
Classifier: Programming Language :: Python :: 2.7
Classifier: Programming Language :: Python :: 3.5
Classifier: Programming Language :: Python :: 3.6
Classifier: Programming Language :: Python :: 3.7
Requires-Dist: nanome
